sqlalchemy_upsert_kit/__init__.py
sqlalchemy_upsert_kit/_version.py
sqlalchemy_upsert_kit/api.py
sqlalchemy_upsert_kit/exc.py
sqlalchemy_upsert_kit/paths.py
sqlalchemy_upsert_kit/sqlite/__init__.py
sqlalchemy_upsert_kit/sqlite/api.py
sqlalchemy_upsert_kit/sqlite/executor.py
sqlalchemy_upsert_kit/sqlite/insert_or_ignore.py
sqlalchemy_upsert_kit/sqlite/insert_or_merge.py
sqlalchemy_upsert_kit/sqlite/insert_or_replace.py
sqlalchemy_upsert_kit/utils.py
sqlalchemy_upsert_kit/vendor/__init__.py
sqlalchemy_upsert_kit/vendor/pytest_cov_helper.py
sqlalchemy_upsert_kit-0.1.1.dist-info/AUTHORS.rst
sqlalchemy_upsert_kit-0.1.1.dist-info/LICENSE.txt
sqlalchemy_upsert_kit-0.1.1.dist-info/METADATA
sqlalchemy_upsert_kit-0.1.1.dist-info/WHEEL
sqlalchemy_upsert_kit-0.1.1.dist-info/RECORD
